AUTHORS
LICENSE
MANIFEST.in
README.creole
setup.py
contactstore/__init__.py
contactstore/models.py
contactstore/tools.py
contactstore/urls.py
contactstore/views.py
contactstore/openinviter/__init__.py
contactstore/openinviter/invitercmd.py
contactstore/openinviter/php/script.php
contactstore/openinviter/php/OpenInviter/LICENSE.txt
contactstore/openinviter/php/OpenInviter/POLICY.txt
contactstore/openinviter/php/OpenInviter/autoupdate.php
contactstore/openinviter/php/OpenInviter/config.php
contactstore/openinviter/php/OpenInviter/default.php
contactstore/openinviter/php/OpenInviter/example.php
contactstore/openinviter/php/OpenInviter/index.htm
contactstore/openinviter/php/OpenInviter/index.html
contactstore/openinviter/php/OpenInviter/index.php
contactstore/openinviter/php/OpenInviter/install.txt
contactstore/openinviter/php/OpenInviter/install_visual.pdf
contactstore/openinviter/php/OpenInviter/not_postinstall.php
contactstore/openinviter/php/OpenInviter/notifier.php
contactstore/openinviter/php/OpenInviter/openinviter.php
contactstore/openinviter/php/OpenInviter/postinstall_results.res
contactstore/openinviter/php/OpenInviter/stats.php
contactstore/openinviter/php/OpenInviter/conf/_hosted.conf
contactstore/openinviter/php/OpenInviter/conf/abv.conf
contactstore/openinviter/php/OpenInviter/conf/aol.conf
contactstore/openinviter/php/OpenInviter/conf/apropo.conf
contactstore/openinviter/php/OpenInviter/conf/atlas.conf
contactstore/openinviter/php/OpenInviter/conf/aussiemail.conf
contactstore/openinviter/php/OpenInviter/conf/azet.conf
contactstore/openinviter/php/OpenInviter/conf/badoo.conf
contactstore/openinviter/php/OpenInviter/conf/bebo.conf
contactstore/openinviter/php/OpenInviter/conf/bigstring.conf
contactstore/openinviter/php/OpenInviter/conf/bookcrossing.conf
contactstore/openinviter/php/OpenInviter/conf/bordermail.conf
contactstore/openinviter/php/OpenInviter/conf/brazencareerist.conf
contactstore/openinviter/php/OpenInviter/conf/canoe.conf
django_contactstore.egg-info/PKG-INFO
django_contactstore.egg-info/SOURCES.txt
django_contactstore.egg-info/dependency_links.txt
django_contactstore.egg-info/entry_points.txt
django_contactstore.egg-info/top_level.txt