Metadata-Version: 1.0
Name: django-contactstore
Version: 0.1.5
Summary: an openinviter based contact importer
Home-page: http://github.com/woome/django-contactstore
Author: Nic Ferrier
Author-email: nic@woome.com
License: GPLv2
Download-URL: http://github.com/woome/django-contactstore/downloads
Platform: unix
Classifier: Development Status :: 3 - Alpha
Classifier: Intended Audience :: Developers
Classifier: License :: OSI Approved :: BSD License
Classifier: Operating System :: OS Independent
Classifier: Programming Language :: Python
Classifier: Topic :: Utilities
Classifier: Topic :: Communications :: Email
